metrax/__init__.py
metrax/audio_metrics.py
metrax/base.py
metrax/classification_metrics.py
metrax/image_metrics.py
metrax/nlp_metrics.py
metrax/ranking_metrics.py
metrax/regression_metrics.py
metrax/logging/__init__.py
metrax/logging/protocol.py
metrax/logging/tensorboard_backend.py
metrax/logging/wandb_backend.py
metrax/nnx/__init__.py
metrax/nnx/nnx_metrics.py
metrax/nnx/nnx_wrapper.py
google_metrax-0.2.4.dist-info/METADATA
google_metrax-0.2.4.dist-info/WHEEL
google_metrax-0.2.4.dist-info/licenses/LICENSE
google_metrax-0.2.4.dist-info/RECORD
