Metadata-Version: 2.4
Name: google_metrax
Version: 0.2.4
Summary: A centralized JAX metrics library.
Project-URL: Homepage, https://github.com/google/metrax
Project-URL: Issues, https://github.com/google/metrax/issues
Author-email: Jiwon Shin <jshin1394@gmail.com>
License: 
License-File: LICENSE
Classifier: Operating System :: OS Independent
Classifier: Programming Language :: Python :: 3
Requires-Python: >=3.8
Requires-Dist: clu>=0.0.12
Requires-Dist: flax>=0.11.1
Requires-Dist: jax>=0.6.2
Requires-Dist: numpy>=2.1.3
Requires-Dist: tensorboardx>=2.6.4
Provides-Extra: dev
Requires-Dist: absl-py>=2.3.1; extra == 'dev'
Requires-Dist: jax-tpu-embedding==0.1.0.dev20250618; extra == 'dev'
Requires-Dist: jax[cpu]==0.6.2; extra == 'dev'
Requires-Dist: keras-hub; extra == 'dev'
Requires-Dist: keras-rs>=0.2.1; extra == 'dev'
Requires-Dist: nltk>=3.9.1; extra == 'dev'
Requires-Dist: pillow>=9.0.0; extra == 'dev'
Requires-Dist: protobuf>=5.29.5; extra == 'dev'
Requires-Dist: pytest>=8.4.1; extra == 'dev'
Requires-Dist: rouge-score>=0.1.2; extra == 'dev'
Requires-Dist: scikit-learn>=1.7.1; extra == 'dev'
Requires-Dist: tensorflow; extra == 'dev'
Requires-Dist: torchmetrics>=1.8.1; extra == 'dev'
Provides-Extra: docs
Requires-Dist: myst-nb; extra == 'docs'
Requires-Dist: scikit-learn==1.6.1; extra == 'docs'
Requires-Dist: sphinx-book-theme; extra == 'docs'
